MT_PY_Performancelogging/MT_Performance.py
MT_PY_Performancelogging/__init__.py
MT_PY_Performancelogging/testcode.py
MT_PY_PerformanceLogging-0.0.1.dist-info/LICENSE.txt
MT_PY_PerformanceLogging-0.0.1.dist-info/METADATA
MT_PY_PerformanceLogging-0.0.1.dist-info/WHEEL
MT_PY_PerformanceLogging-0.0.1.dist-info/top_level.txt
MT_PY_PerformanceLogging-0.0.1.dist-info/RECORD
